Metadata-Version: 1.1
Name: fancymath
Version: 1.0
Summary: Unicode math for the lazy TeXnician
Home-page: UNKNOWN
Author: Andrea Censi
Author-email: censi@mit.edu
License: GPL
Keywords: latex math unicode
Platform: UNKNOWN
Classifier: Development Status :: 3 - Alpha
Classifier: Topic :: Utilities
